{
  "context-menu": {
    "atom-workspace": [
      {
        "label": "Footsize",
        "submenu": [
          {"label": "Include snippet", "command": "footsize:html5"},
          {"type": "separator"},
          {"label": "Deleted Selected Text", "command": "core:delete"}
        ]
      }
    ]
  },
  "menu": [
    {
      "label": "Packages",
      "submenu": [
        {
          "label": "footsize",
          "submenu": [
            {
              "label": "Convert",
              "command": "footsize:convert"
            }
          ]
        }
      ]
    }
  ]
}
